COPYING
README.md
setup.cfg
setup.py
src/nemu/__init__.py
src/nemu/compat.py
src/nemu/environ.py
src/nemu/interface.py
src/nemu/iproute.py
src/nemu/node.py
src/nemu/passfd.py
src/nemu/protocol.py
src/nemu/subprocess_.py
src/nemu3.egg-info/PKG-INFO
src/nemu3.egg-info/SOURCES.txt
src/nemu3.egg-info/dependency_links.txt
src/nemu3.egg-info/requires.txt
src/nemu3.egg-info/top_level.txt
test/test_core.py
test/test_interfaces.py
test/test_node.py
test/test_protocol.py
test/test_routing.py
test/test_subprocess.py
test/test_switch.py
test/test_util.py