Metadata-Version: 2.1
Name: nemu3
Version: 0.4
Summary: A lightweight network emulator embedded in a small python library.
Home-page: https://lab.nexedi.com/nexedi/nemu3
Author: Martina Ferrari, Alina Quereilhac, Tom Niget
Author-email: tina@tina.pm, aquereilhac@gmail.com, tom.niget@nexedi.com
License: GPLv2
Platform: Linux
Classifier: Development Status :: 4 - Beta
Classifier: Environment :: Console
Classifier: Intended Audience :: Developers
Classifier: License :: OSI Approved :: GNU General Public License v2 (GPLv2)
Classifier: Operating System :: POSIX :: Linux
Classifier: Programming Language :: Python :: 3
Classifier: Topic :: System :: Networking
Requires-Python: >=3.11
License-File: COPYING
Requires-Dist: unshare
Requires-Dist: six
Requires-Dist: attrs
